oaktreemodel/__init__.py
oaktreemodel/common.proto
oaktreemodel/common_pb2.py
oaktreemodel/flavor.proto
oaktreemodel/flavor_pb2.py
oaktreemodel/floating_ip.proto
oaktreemodel/floating_ip_pb2.py
oaktreemodel/image.proto
oaktreemodel/image_pb2.py
oaktreemodel/model.py
oaktreemodel/oaktree.proto
oaktreemodel/oaktree_pb2.py
oaktreemodel/security_group.proto
oaktreemodel/security_group_pb2.py
oaktreemodel-0.0.2.dist-info/DESCRIPTION.rst
oaktreemodel-0.0.2.dist-info/METADATA
oaktreemodel-0.0.2.dist-info/RECORD
oaktreemodel-0.0.2.dist-info/WHEEL
oaktreemodel-0.0.2.dist-info/metadata.json
oaktreemodel-0.0.2.dist-info/pbr.json
oaktreemodel-0.0.2.dist-info/top_level.txt
